[{"_path":"/guides/initiating-refunds","_dir":"guides","_draft":false,"_partial":false,"_locale":"en","_empty":false,"title":"Initiating Refunds","description":"How to issue refunds on the Centrapay payment platform.","nav":{"path":"Reference/Merchant Integrations","order":7},"_type":"markdown","_id":"content:guides:initiating-refunds.md","_source":"content","_file":"guides/initiating-refunds.md","_extension":"md"},{"_path":"/guides/merchant-integration-barcode-flow","_dir":"guides","_draft":false,"_partial":false,"_locale":"en","_empty":false,"title":"Barcode Flow for Merchants","description":"How merchants can accept payments by scanning a barcode presented by the patron.","nav":{"path":"Reference/Merchant Integrations","title":"Barcode Flow","order":4},"_type":"markdown","_id":"content:guides:merchant-integration-barcode-flow.md","_source":"content","_file":"guides/merchant-integration-barcode-flow.md","_extension":"md"}]