[{"title":"Guides","_path":"/guides","children":[{"title":"Creating Test Money","_path":"/guides/creating-test-money"},{"title":"eCommerce","_path":"/guides/ecommerce-website"},{"title":"Example OIDC Consumer","_path":"/guides/example-oidc-consumer"},{"title":"Farmlands POS Integration Guide","_path":"/guides/farmlands-pos-integration"},{"title":"Initiating Refunds","_path":"/guides/initiating-refunds"},{"title":"Line Items","_path":"/guides/line-items"},{"title":"Loading and Sending Assets","_path":"/guides/loading-and-sending-assets"},{"title":"Barcode Flow for Merchants","_path":"/guides/merchant-integration-barcode-flow"},{"title":"Merchant Integration Error Handling","_path":"/guides/merchant-integration-error-handling"},{"title":"QR Code Flow for Merchants","_path":"/guides/merchant-integration-qr-code-flow"},{"title":"Patron Not Present","_path":"/guides/patron-not-present"},{"title":"Payment Conditions","_path":"/guides/payment-conditions"},{"title":"Point of Sale","_path":"/guides/point-of-sale"},{"title":"Requesting Payment","_path":"/guides/requesting-payment"},{"title":"Requesting Pre Auth","_path":"/guides/requesting-pre-auth"},{"title":"Transaction Reporting","_path":"/guides/transaction-reporting"}]}]